{
  "collapse-filter": false,
  "search": "",
  "showTags": true,
  "showAttachments": false,
  "hideUnresolved": false,
  "showOrphans": true,
  "collapse-color-groups": false,
  "colorGroups": [
    {
      "query": "path:Characters  ",
      "color": {
        "a": 1,
        "rgb": 5746932
      }
    },
    {
      "query": "path:Groups  ",
      "color": {
        "a": 1,
        "rgb": 12425691
      }
    },
    {
      "query": "path:Clues  ",
      "color": {
        "a": 1,
        "rgb": 14703442
      }
    }
  ],
  "collapse-display": false,
  "showArrow": false,
  "textFadeMultiplier": -1,
  "nodeSizeMultiplier": 1,
  "lineSizeMultiplier": 0.996716369265868,
  "collapse-forces": false,
  "centerStrength": 0.329259349792227,
  "repelStrength": 12.5250549987778,
  "linkStrength": 1,
  "linkDistance": 158,
  "scale": 0.6345223601615421,
  "close": true
}